{
  "id": "00932",
  "text": "在平面直角坐标系中，抛物线y=-(1/4)x²+(3/2)x+4与x轴交于A、B两点，与y轴交于点C，抛物线的对称轴与x轴交于点D",
  "dsl": [
    "point(A)",
    "point(B)",
    "point(C)",
    "point(D)",
    "coordinate_system(O)",
    "point_coord(O, 0, 0)",
    "point_coord(A, -2, 0)",
    "point_coord(B, 8, 0)",
    "point_coord(C, 0, 4)",
    "point_coord(D, 3, 0)",
    "parabola(p1, -0.25, 1.5, 4)",
    "segment(AB)",
    "segment(AC)",
    "segment(BC)",
    "on(A, axis_x)",
    "on(B, axis_x)",
    "on(C, axis_y)",
    "on(D, axis_x)",
    "function_point(A, p1)",
    "function_point(B, p1)",
    "function_point(C, p1)"
  ],
  "image_path": "images/00932.png",
  "geometry": {
    "points": {},
    "constraints": []
  },
  "meta": {
    "source": "抛物线对称轴与坐标轴",
    "difficulty": "hard",
    "tags": ["coordinate", "parabola"]
  }
}