{
  "id": "00942",
  "text": "在平面直角坐标系中，抛物线y=-x^2+4与x轴交于点A、B，与y轴交于点C，P为x轴下方抛物线上一点，OA=2，OC=4",
  "dsl": [
    "point(A)",
    "point(B)",
    "point(C)",
    "point(P)",
    "coordinate_system(O)",
    "point_coord(O, 0, 0)",
    "point_coord(A, -2, 0)",
    "point_coord(B, 2, 0)",
    "point_coord(C, 0, 4)",
    "parabola(p1, -1, 0, 4)",
    "segment(AB)",
    "segment(AC)",
    "segment(BC)",
    "on(A, axis_x)",
    "on(B, axis_x)",
    "on(C, axis_y)",
    "function_point(A, p1)",
    "function_point(B, p1)",
    "function_point(C, p1)",
    "ratio(OC, OA)=2",
    "length(OC)=4"
  ],
  "image_path": "images/00942.png",
  "geometry": {
    "points": {},
    "constraints": []
  },
  "meta": {
    "source": "抛物线对称轴与角度",
    "difficulty": "hard",
    "tags": ["coordinate", "parabola"]
  }
}